genpasswd/__init__.py
genpasswd/__main__.py
genpasswd/constants.py
genpasswd/exceptions.py
genpasswd/genpasswd.py
genpasswd-1.3.5.dist-info/LICENSE
genpasswd-1.3.5.dist-info/METADATA
genpasswd-1.3.5.dist-info/WHEEL
genpasswd-1.3.5.dist-info/entry_points.txt
genpasswd-1.3.5.dist-info/top_level.txt
genpasswd-1.3.5.dist-info/RECORD
